utils_cws_web/__init__.py
utils_cws_web/integration.py
utils_cws_web/middleware.py
utils_cws_web/dto/__init__.py
utils_cws_web/dto/dto_data.py
utils_cws_web/dto/schema_error.py
utils_cws_web/dto/schema_registry.py
utils_cws_web/exception/__init__.py
utils_cws_web/exception/integration_error.py
utils_cws_web/exception/schema_exception.py
Utils_cws_web-1.0.3.dist-info/LICENCE
Utils_cws_web-1.0.3.dist-info/METADATA
Utils_cws_web-1.0.3.dist-info/WHEEL
Utils_cws_web-1.0.3.dist-info/top_level.txt
Utils_cws_web-1.0.3.dist-info/RECORD
