Metadata-Version: 2.1
Name: Utils-cws-web
Version: 1.0.3
Summary: It's a package that contains utilities for web development.
Home-page: https://github.com/ConectarWali/
Author: Conectar Wali SAS
Author-email: dev@conectarwalisas.com.co
Classifier: Programming Language :: Python :: 3
Classifier: License :: OSI Approved :: MIT License
Classifier: Operating System :: OS Independent
Requires-Python: >=3.6
License-File: LICENCE
